gevent_grpc_monkey_patch/__init__.py
gevent_grpc_monkey_patch-0.0.3.dist-info/METADATA
gevent_grpc_monkey_patch-0.0.3.dist-info/WHEEL
gevent_grpc_monkey_patch-0.0.3.dist-info/top_level.txt
gevent_grpc_monkey_patch-0.0.3.dist-info/RECORD
